DESCRIPTION
MANIFEST.in
README
setup.py
bin/pymmseg
mmseg/__init__.py
mmseg/__init__.pyc
mmseg/_mmseg.so
mmseg/data/chars.dic
mmseg/data/words.dic
mmseg/mmseg-cpp/algor.cpp
mmseg/mmseg-cpp/algor.h
mmseg/mmseg-cpp/build.py
mmseg/mmseg-cpp/chunk.h
mmseg/mmseg-cpp/dict.cpp
mmseg/mmseg-cpp/dict.h
mmseg/mmseg-cpp/memory.cpp
mmseg/mmseg-cpp/memory.h
mmseg/mmseg-cpp/mmseg.cpp
mmseg/mmseg-cpp/rules.h
mmseg/mmseg-cpp/token.h
mmseg/mmseg-cpp/utils.h
mmseg/mmseg-cpp/word.h
pymmseg.egg-info/PKG-INFO
pymmseg.egg-info/SOURCES.txt
pymmseg.egg-info/dependency_links.txt
pymmseg.egg-info/top_level.txt