Metadata-Version: 1.0
Name: pymmseg
Version: 1.2.0
Summary: pyMMSeg-cpp, a high performance Chinese word segmentation utility.
Home-page: http://github.com/pluskid/pymmseg-cpp
Author: pluskid & kronuz & zsp007
Author-email: pluskid@gmail.com
License: MIT
Download-URL: https://github.com/pluskid/pymmseg-cpp/archive/master.tar.gz
Keywords: mmseg chinese word segmentation tokenization
Platform: UNKNOWN
Classifier: Development Status :: 5 - Production/Stable
Classifier: Intended Audience :: Developers
Classifier: License :: OSI Approved :: MIT License
Classifier: Operating System :: OS Independent
Classifier: Programming Language :: Python
Classifier: Programming Language :: Python :: 3
Classifier: Topic :: Text Processing
Classifier: Topic :: Software Development :: Libraries :: Python Modules
